{
    "title": {
        "media": {
          "url": "/archives-exhibits-demo/archives-exhibits-demo/objects/becoming-caltech-feature.webp",
          "caption": null,
          "credit": "Becoming Caltech"
        },
        "text": {
          "headline": "Becoming Caltech Timeline",
          "text": "The cast stone arches by Alexander Calder that adorned Caltech’s Throop Hall fell victim, as did the building itself, to the 1971 San Fernando earthquake."
        }
    },
    "events": [
      {
        "media": {
          "url": "/archives-exhibits-demo/objects/greater-throop-collection/greater-throop-1/greater-throop-1-small.jpg",
          "caption": "Wood Carving Class",
          "link": "/archives-exhibits-demo/items/greater-throop-1.html"
        },
        "start_date": { 
          
          "year": "1890s"
        },
        "text": {
          "headline": "Wood Carving Class",
          "text": "Unknown photographer. Wood Carving Class, 1890s."
        }
      },{
        "media": {
          "url": "/archives-exhibits-demo/objects/greater-throop-collection/greater-throop-2/greater-throop-2-small.jpg",
          "caption": "Unknown photographer, Drawing Class, 1890s",
          "link": "/archives-exhibits-demo/items/greater-throop-2.html"
        },
        "start_date": { 
          
          "year": "1890s"
        },
        "text": {
          "headline": "Unknown photographer, Drawing Class, 1890s",
          "text": "Unknown photographer. Drawing Class, 1890s."
        }
      },{
        "media": {
          "url": "/archives-exhibits-demo/objects/greater-throop-collection/greater-throop-3/greater-throop-3-small.jpg",
          "caption": "George Ellery Hale at the Mount Wilson Observatory Snow Solar Telescope Spectrograph",
          "link": "/archives-exhibits-demo/items/greater-throop-3.html"
        },
        "start_date": { 
          
          "year": "c. 1905"
        },
        "text": {
          "headline": "George Ellery Hale at the Mount Wilson Observatory Snow Solar Telescope Spectrograph",
          "text": "Unknown photographer. George Ellery Hale at the Mount Wilson Observatory Snow Solar Telescope Spectrograph, c. 1905."
        }
      },{
        "media": {
          "url": "/archives-exhibits-demo/objects/greater-throop-collection/greater-throop-4/greater-throop-4-small.jpg",
          "caption": "James Augustin Brown Scherer",
          "link": "/archives-exhibits-demo/items/greater-throop-4.html"
        },
        "start_date": { 
          
          "year": "April 1918"
        },
        "text": {
          "headline": "James Augustin Brown Scherer",
          "text": "Unknown photographer. James Augustin Brown Scherer, April 1918."
        }
      },{
        "media": {
          "url": "/archives-exhibits-demo/objects/greater-throop-collection/greater-throop-7/greater-throop-7-small.jpg",
          "caption": "Throop Pennant",
          "link": "/archives-exhibits-demo/items/greater-throop-7.html"
        },
        "start_date": { 
          
          "year": "c. 1910"
        },
        "text": {
          "headline": "Throop Pennant",
          "text": "Unknown maker. Throop Pennant, c. 1910 Felt."
        }
      }
    ]
}
